cache_manager/__init__.py
cache_manager/cache_manager.py
cache_manager/cache_manager_factory.py
cache_manager/adapters/__init__.py
cache_manager/adapters/memcached_cache_manager.py
cache_manager/adapters/redis_cache_manager.py
python_cache_manager-0.1.0.dist-info/LICENSE
python_cache_manager-0.1.0.dist-info/METADATA
python_cache_manager-0.1.0.dist-info/WHEEL
python_cache_manager-0.1.0.dist-info/top_level.txt
python_cache_manager-0.1.0.dist-info/RECORD
